csv_mqtt/__init__.py
csv_mqtt/csv_mqtt.py
csv_mqtt-1.0.2.dist-info/LICENSE
csv_mqtt-1.0.2.dist-info/METADATA
csv_mqtt-1.0.2.dist-info/WHEEL
csv_mqtt-1.0.2.dist-info/top_level.txt
csv_mqtt-1.0.2.dist-info/RECORD
