Metadata-Version: 2.1
Name: csv-mqtt
Version: 1.0.2
Summary: CSV parser meets MQTT Publisher
Home-page: https://github.com/srijan-sivakumar/CSV-MQTT/
Author: srijan-sivakumar
Author-email: sivakumarsrijan@gmail.com
License: UNKNOWN
Platform: UNKNOWN
Classifier: Programming Language :: Python :: 3
Classifier: License :: OSI Approved :: MIT License
Classifier: Operating System :: OS Independent
Requires-Dist: paho-mqtt
